d20/__init__.py
d20/__main__.py
d20/dice.py
d20/diceast.py
d20/errors.py
d20/expression.py
d20/grammar.lark
d20/rand.py
d20/stringifiers.py
d20/utils.py
apollo_d20-1.2.1.dist-info/METADATA
apollo_d20-1.2.1.dist-info/WHEEL
apollo_d20-1.2.1.dist-info/licenses/LICENSE
apollo_d20-1.2.1.dist-info/RECORD
