Metadata-Version: 2.3
Name: apollo-d20
Version: 1.2.1
Summary: A fork of d20 to be used with PYTHIA. 
Project-URL: Homepage, https://github.com/AstreaTSS/apollo-d20
Project-URL: Bug Tracker, https://github.com/AstreaTSS/apollo-d20/issues
Author: AstreaTSS
Author-email: Andrew Zhu <andrew@zhu.codes>
License: MIT License
License-File: LICENSE
Classifier: Development Status :: 5 - Production/Stable
Classifier: License :: OSI Approved :: MIT License
Classifier: Operating System :: OS Independent
Classifier: Programming Language :: Python :: 3
Classifier: Topic :: Games/Entertainment :: Board Games
Classifier: Topic :: Games/Entertainment :: Role-Playing
Requires-Python: >=3.6
Requires-Dist: cachetools<6.0.0,>=3.1.0
Requires-Dist: lark<2.0.0,>=0.9.0
Provides-Extra: numpy
Requires-Dist: numpy<3.0.0,>=1.17.0; extra == 'numpy'
